{
  "parent": "minecraft:recipes/root",
  "rewards": {
    "recipes": [
      "kawaiidishes:orange_maid_dress_fox_tail_red"
    ]
  },
  "criteria": {
    "has_orange_maid_dress": {
      "trigger": "minecraft:inventory_changed",
      "conditions": {
        "items": [
          {
            "items": [
              "kawaiidishes:orange_maid_dress"
            ]
          }
        ]
      }
    },
    "has_the_recipe": {
      "trigger": "minecraft:recipe_unlocked",
      "conditions": {
        "recipe": "kawaiidishes:orange_maid_dress_fox_tail_red"
      }
    }
  },
  "requirements": [
    [
      "has_orange_maid_dress",
      "has_the_recipe"
    ]
  ]
}